func_timeouts
