Metadata-Version: 1.2
Name: func-timeouts
Version: 1.0.2
Summary: Fork of [func_timeout]. Fixes some Exception issues and creates a new decorator for when you always want to specify a timeout value.
Home-page: https://github.com/BrianHVB/func_timeouts.git
Author: Brian Houle
Author-email: grimzecho@gmail.com
Maintainer: Brian Houle
Maintainer-email: grimzecho@gmail.com
License: LGPLv2
Keywords: timeout
Platform: UNKNOWN
Classifier: Development Status :: 5 - Production/Stable
Classifier: Programming Language :: Python
Classifier: License :: OSI Approved :: GNU Lesser General Public License v2 (LGPLv2)
Classifier: Programming Language :: Python :: 2
Classifier: Programming Language :: Python :: 2.7
Classifier: Programming Language :: Python :: 3.4
Classifier: Programming Language :: Python :: 3.5
Classifier: Programming Language :: Python :: 3.6
Classifier: Programming Language :: Python :: 3.7
Classifier: Topic :: Software Development :: Libraries :: Python Modules
